{
	"info": {
		"_postman_id": "89ac494d-378d-4f54-90e6-239e8958bb4a",
		"name": "CodeAlpha URL Shortener",
		"description": "API collection for testing the CodeAlpha URL Shortener backend.",
		"schema": "https://schema.getpostman.com/json/collection/v2.1.0/collection.json"
	},
	"item": [
		{
			"name": "Shorten URL",
			"request": {
				"method": "POST",
				"header": [
					{
						"key": "Content-Type",
						"value": "application/json",
						"type": "text"
					}
				],
				"body": {
					"mode": "raw",
					"raw": "{\n    \"originalUrl\": \"https://www.codealpha.in\"\n}"
				},
				"url": {
					"raw": "{{base_url}}/shorten",
					"host": [
						"{{base_url}}"
					],
					"path": [
						"shorten"
					]
				},
				"description": "Generate a short code for a long URL."
			},
			"response": []
		},
		{
			"name": "Redirect Short URL",
			"request": {
				"method": "GET",
				"header": [],
				"url": {
					"raw": "{{base_url}}/:code",
					"host": [
						"{{base_url}}"
					],
					"path": [
						":code"
					],
					"variable": [
						{
							"key": "code",
							"value": "k8Xp2Y9z",
							"description": "The short code generated by /shorten"
						}
					]
				},
				"description": "Redirects to the original URL associated with the short code."
			},
			"response": []
		},
		{
			"name": "Get URL Stats",
			"request": {
				"method": "GET",
				"header": [],
				"url": {
					"raw": "{{base_url}}/stats/:code",
					"host": [
						"{{base_url}}"
					],
					"path": [
						"stats",
						":code"
					],
					"variable": [
						{
							"key": "code",
							"value": "k8Xp2Y9z",
							"description": "The short code generated by /shorten"
						}
					]
				},
				"description": "Get analytics (click counts, creation date, original URL) for a shortened URL."
			},
			"response": []
		}
	],
	"event": [
		{
			"listen": "prerequest",
			"script": {
				"type": "text/javascript",
				"exec": [
					""
				]
			}
		},
		{
			"listen": "test",
			"script": {
				"type": "text/javascript",
				"exec": [
					""
				]
			}
		}
	],
	"variable": [
		{
			"key": "base_url",
			"value": "http://localhost:5000",
			"type": "string"
		}
	]
}
